setup.cfg
setup.py
lmi/__init__.py
lmi/scripts/__init__.py
lmi/scripts/selinux/__init__.py
lmi/scripts/selinux/cmd.py
openlmi_scripts_selinux.egg-info/PKG-INFO
openlmi_scripts_selinux.egg-info/SOURCES.txt
openlmi_scripts_selinux.egg-info/dependency_links.txt
openlmi_scripts_selinux.egg-info/entry_points.txt
openlmi_scripts_selinux.egg-info/namespace_packages.txt
openlmi_scripts_selinux.egg-info/requires.txt
openlmi_scripts_selinux.egg-info/top_level.txt