Metadata-Version: 1.1
Name: openlmi-scripts-selinux
Version: 0.4.0
Summary: SELinux management through OpenLMI selinux providers.
Home-page: https://github.com/openlmi/openlmi-selinux
Author: Vitezslav Crhonek
Author-email: vcrhonek@redhat.com
License: BSD
Download-URL: https://github.com/openlmi/openlmi-selinux/tarball/master
Platform: Any
Classifier: License :: OSI Approved :: BSD License
Classifier: Operating System :: POSIX :: Linux
Classifier: Topic :: System :: Systems Administration
Classifier: Programming Language :: Python
Classifier: Programming Language :: Python :: 2
Classifier: Programming Language :: Python :: 2.7
Classifier: Intended Audience :: Developers
Classifier: Environment :: Console
